{
  "_fv": 5,
  "_type": "item",
  "definition": {
    "renderType": 0,
    "texture": "sound_player_msz",
    "customModelName": "Normal",
    "name": "Mirage Saloon Act 1",
    "creativeTab": {
      "value": "CUSTOM:Items"
    },
    "stackSize": 1,
    "enchantability": 0,
    "useDuration": 0,
    "toolType": 1.0,
    "damageCount": 0,
    "destroyAnyBlock": false,
    "stayInGridWhenCrafting": false,
    "enableMeleeDamage": false,
    "damageVsEntity": 0.0,
    "specialInfo": [
      "Mirage Saloon Zone Act 1 (Wildstyle Pistolero) - Sonic Mania"
    ],
    "hasGlow": true,
    "onRightClickedInAir": {
      "name": "MirageSaloonAct1knuxRightClicked"
    },
    "onRightClickedOnBlock": {
      "name": "MirageSaloonAct1knuxRightClicked"
    }
  }
}