{
  "_fv": 5,
  "_type": "plant",
  "definition": {
    "renderType": 12,
    "texture": "pgz_plant",
    "customModelName": "Cross model",
    "plantType": "normal",
    "growapableSpawnType": "Desert",
    "growapableMaxHeight": 3,
    "name": "PGZ Flower",
    "creativeTab": {
      "value": "CUSTOM:Items"
    },
    "hardness": 0.01,
    "resistance": 2.0,
    "luminance": 0.0,
    "unbreakable": false,
    "soundOnStep": {
      "value": "PLANT"
    },
    "customDrop": {
      "value": ""
    },
    "dropAmount": 1,
    "isReplaceable": false,
    "isFlammable": false,
    "colorOnMap": "DEFAULT",
    "creativePickItem": {
      "value": ""
    },
    "frequencyOnChunks": 20,
    "spawnWorldTypes": [],
    "restrictionBiomes": []
  }
}